LICENSE
README.rst
VERSION
pyproject.toml
conf_engine/__init__.py
conf_engine/__version__.py
conf_engine/configuration.py
conf_engine/options.py
conf_engine.egg-info/PKG-INFO
conf_engine.egg-info/SOURCES.txt
conf_engine.egg-info/dependency_links.txt
conf_engine.egg-info/top_level.txt
conf_engine/core/exceptions.py
conf_engine/core/types.py
conf_engine/core/tests/test_types.py
conf_engine/parsers/__init__.py
conf_engine/parsers/cli.py
conf_engine/parsers/env.py
conf_engine/parsers/ini_file.py
conf_engine/parsers/tests/__init__.py
conf_engine/parsers/tests/test_cli.py
conf_engine/parsers/tests/test_env.py
conf_engine/parsers/tests/test_ini_file.py
conf_engine/tests/__init__.py
conf_engine/tests/conftest.py
conf_engine/tests/test_config.py
conf_engine/tests/test_options.py